rtctools_interface/__init__.py
rtctools_interface/_version.py
rtctools_interface/closed_loop/__init__.py
rtctools_interface/closed_loop/config.py
rtctools_interface/closed_loop/optimization_ranges.py
rtctools_interface/closed_loop/results_construction.py
rtctools_interface/closed_loop/runner.py
rtctools_interface/closed_loop/time_series_handler.py
rtctools_interface/optimization/__init__.py
rtctools_interface/optimization/base_goal.py
rtctools_interface/optimization/base_optimization_problem.py
rtctools_interface/optimization/goal_generator_mixin.py
rtctools_interface/optimization/goal_performance_metrics.py
rtctools_interface/optimization/goal_table_schema.py
rtctools_interface/optimization/plot_goals_mixin.py
rtctools_interface/optimization/plot_mixin.py
rtctools_interface/optimization/read_goals.py
rtctools_interface/optimization/helpers/__init__.py
rtctools_interface/optimization/helpers/statistics_mixin.py
rtctools_interface/plotting/__init__.py
rtctools_interface/plotting/plot_tools.py
rtctools_interface/plotting/subplot_classes.py
rtctools_interface/simulation/__init__.py
rtctools_interface/simulation/base_simulation_problem.py
rtctools_interface/simulation/plot_mixin.py
rtctools_interface/utils/__init__.py
rtctools_interface/utils/plot_table_schema.py
rtctools_interface/utils/read_goals_mixin.py
rtctools_interface/utils/read_plot_table.py
rtctools_interface/utils/results_collection.py
rtctools_interface/utils/serialization.py
rtctools_interface/utils/type_definitions.py
tests/__init__.py
tests/closed_loop/__init__.py
tests/closed_loop/test_optimization_ranges.py
tests/closed_loop/test_read_xml.py
tests/closed_loop/test_run_optization_problem_closed_loop.py
tests/optimization/__init__.py
tests/optimization/test_base_optimization_problem.py
tests/optimization/test_passing_goals_directly.py
tests/optimization/test_plot_goals_mixin.py
tests/optimization/test_read_goals.py
tests/simulation/__init__.py
tests/simulation/test_base_simulation_problem.py
rtc_tools_interface-0.10.1.dist-info/COPYING.LESSER
rtc_tools_interface-0.10.1.dist-info/METADATA
rtc_tools_interface-0.10.1.dist-info/WHEEL
rtc_tools_interface-0.10.1.dist-info/top_level.txt
rtc_tools_interface-0.10.1.dist-info/RECORD
