Metadata-Version: 2.1
Name: rtc-tools-interface
Version: 0.10.1
Summary: Toolbox for user interfaces for RTC-Tools
Home-page: UNKNOWN
Author: Deltares
Maintainer: Deltares
License: UNKNOWN
Platform: UNKNOWN
Requires-Python: >=3.9
License-File: COPYING.LESSER
